Metadata-Version: 2.1
Name: nikitos-package
Version: 0.0.2
Summary: This is a test package
Home-page: UNKNOWN
Author: Nikita Romm
Author-email: nikitaromm@gmail.com
License: UNKNOWN
Platform: UNKNOWN
Classifier: Programming Language :: Python :: 3
Classifier: License :: OSI Approved :: MIT License
Classifier: Operating System :: OS Independent
Requires-Python: >=3.6
